{"data":{"site":{"siteMetadata":{"title":"Ham's Lecture notes","author":"Tanyawat Vittayapalotai"}},"markdownRemark":{"id":"/builds/hamzaabamboo/2nd-year-lecture-notes/lecture-notes/src/pages/notes/advanced-computer-programming/01-Introduction.md absPath of file >>> MarkdownRemark","htmlAst":{"type":"root","children":[{"type":"element","tagName":"h1","properties":{"id":"instructors"},"children":[{"type":"element","tagName":"a","properties":{"href":"#instructors","ariaHidden":true,"className":["anchor"]},"children":[{"type":"element","tagName":"svg","properties":{"ariaHidden":"true","height":16,"version":"1.1","viewBox":"0 0 16 16","width":16},"children":[{"type":"element","tagName":"path","properties":{"fillRule":"evenodd","d":"M4 9h1v1H4c-1.5 0-3-1.69-3-3.5S2.55 3 4 3h4c1.45 0 3 1.69 3 3.5 0 1.41-.91 2.72-2 3.25V8.59c.58-.45 1-1.27 1-2.09C10 5.22 8.98 4 8 4H4c-.98 0-2 1.22-2 2.5S3 9 4 9zm9-3h-1v1h1c1 0 2 1.22 2 2.5S13.98 12 13 12H9c-.98 0-2-1.22-2-2.5 0-.83.42-1.64 1-2.09V6.25c-1.09.53-2 1.84-2 3.25C6 11.31 7.55 13 9 13h4c1.45 0 3-1.69 3-3.5S14.5 6 13 6z"},"children":[]}]}]},{"type":"text","value":"Instructors"}]},{"type":"text","value":"\n"},{"type":"element","tagName":"ul","properties":{},"children":[{"type":"text","value":"\n"},{"type":"element","tagName":"li","properties":{},"children":[{"type":"text","value":"Sukree Sinthupinyo ( Sukree.S@cp.chula.ac.th )"}]},{"type":"text","value":"\n"},{"type":"element","tagName":"li","properties":{},"children":[{"type":"text","value":"Pitchaya Sitthi-amorn"}]},{"type":"text","value":"\n"}]},{"type":"text","value":"\n"},{"type":"element","tagName":"h1","properties":{"id":"moving-beyond-2190101--computer-programming-"},"children":[{"type":"element","tagName":"a","properties":{"href":"#moving-beyond-2190101--computer-programming-","ariaHidden":true,"className":["anchor"]},"children":[{"type":"element","tagName":"svg","properties":{"ariaHidden":"true","height":16,"version":"1.1","viewBox":"0 0 16 16","width":16},"children":[{"type":"element","tagName":"path","properties":{"fillRule":"evenodd","d":"M4 9h1v1H4c-1.5 0-3-1.69-3-3.5S2.55 3 4 3h4c1.45 0 3 1.69 3 3.5 0 1.41-.91 2.72-2 3.25V8.59c.58-.45 1-1.27 1-2.09C10 5.22 8.98 4 8 4H4c-.98 0-2 1.22-2 2.5S3 9 4 9zm9-3h-1v1h1c1 0 2 1.22 2 2.5S13.98 12 13 12H9c-.98 0-2-1.22-2-2.5 0-.83.42-1.64 1-2.09V6.25c-1.09.53-2 1.84-2 3.25C6 11.31 7.55 13 9 13h4c1.45 0 3-1.69 3-3.5S14.5 6 13 6z"},"children":[]}]}]},{"type":"text","value":"Moving Beyond 2190101 ( Computer Programming )"}]},{"type":"text","value":"\n"},{"type":"element","tagName":"ul","properties":{},"children":[{"type":"text","value":"\n"},{"type":"element","tagName":"li","properties":{},"children":[{"type":"text","value":"Learn New programming concepts."}]},{"type":"text","value":"\n"},{"type":"element","tagName":"li","properties":{},"children":[{"type":"text","value":"Programs in "},{"type":"element","tagName":"strong","properties":{},"children":[{"type":"text","value":"standard framework"}]}]},{"type":"text","value":"\n"},{"type":"element","tagName":"li","properties":{},"children":[{"type":"text","value":"Apply concept "},{"type":"element","tagName":"strong","properties":{},"children":[{"type":"text","value":"between frameworks"}]}]},{"type":"text","value":"\n"},{"type":"element","tagName":"li","properties":{},"children":[{"type":"text","value":"Develop "},{"type":"element","tagName":"strong","properties":{},"children":[{"type":"text","value":"Ready-to-ship"}]},{"type":"text","value":" application ( through class project )"}]},{"type":"text","value":"\n"},{"type":"element","tagName":"li","properties":{},"children":[{"type":"element","tagName":"strong","properties":{},"children":[{"type":"text","value":"Full-stack application"}]}]},{"type":"text","value":"\n"}]},{"type":"text","value":"\n"},{"type":"element","tagName":"h1","properties":{"id":"corequisite-courses"},"children":[{"type":"element","tagName":"a","properties":{"href":"#corequisite-courses","ariaHidden":true,"className":["anchor"]},"children":[{"type":"element","tagName":"svg","properties":{"ariaHidden":"true","height":16,"version":"1.1","viewBox":"0 0 16 16","width":16},"children":[{"type":"element","tagName":"path","properties":{"fillRule":"evenodd","d":"M4 9h1v1H4c-1.5 0-3-1.69-3-3.5S2.55 3 4 3h4c1.45 0 3 1.69 3 3.5 0 1.41-.91 2.72-2 3.25V8.59c.58-.45 1-1.27 1-2.09C10 5.22 8.98 4 8 4H4c-.98 0-2 1.22-2 2.5S3 9 4 9zm9-3h-1v1h1c1 0 2 1.22 2 2.5S13.98 12 13 12H9c-.98 0-2-1.22-2-2.5 0-.83.42-1.64 1-2.09V6.25c-1.09.53-2 1.84-2 3.25C6 11.31 7.55 13 9 13h4c1.45 0 3-1.69 3-3.5S14.5 6 13 6z"},"children":[]}]}]},{"type":"text","value":"Corequisite Courses"}]},{"type":"text","value":"\n"},{"type":"element","tagName":"ul","properties":{},"children":[{"type":"text","value":"\n"},{"type":"element","tagName":"li","properties":{},"children":[{"type":"text","value":"Advanced Computer Programming ( 2190102 )"}]},{"type":"text","value":"\n"},{"type":"element","tagName":"li","properties":{},"children":[{"type":"text","value":"\n"},{"type":"element","tagName":"p","properties":{},"children":[{"type":"text","value":"Advanced Computer Programming Lab ( 2190152 )"}]},{"type":"text","value":"\n"},{"type":"element","tagName":"blockquote","properties":{},"children":[{"type":"text","value":"\n"},{"type":"element","tagName":"p","properties":{},"children":[{"type":"text","value":"Register/ Withdraw Both !"}]},{"type":"text","value":"\n"}]},{"type":"text","value":"\n"}]},{"type":"text","value":"\n"}]},{"type":"text","value":"\n"},{"type":"element","tagName":"h1","properties":{"id":"lms"},"children":[{"type":"element","tagName":"a","properties":{"href":"#lms","ariaHidden":true,"className":["anchor"]},"children":[{"type":"element","tagName":"svg","properties":{"ariaHidden":"true","height":16,"version":"1.1","viewBox":"0 0 16 16","width":16},"children":[{"type":"element","tagName":"path","properties":{"fillRule":"evenodd","d":"M4 9h1v1H4c-1.5 0-3-1.69-3-3.5S2.55 3 4 3h4c1.45 0 3 1.69 3 3.5 0 1.41-.91 2.72-2 3.25V8.59c.58-.45 1-1.27 1-2.09C10 5.22 8.98 4 8 4H4c-.98 0-2 1.22-2 2.5S3 9 4 9zm9-3h-1v1h1c1 0 2 1.22 2 2.5S13.98 12 13 12H9c-.98 0-2-1.22-2-2.5 0-.83.42-1.64 1-2.09V6.25c-1.09.53-2 1.84-2 3.25C6 11.31 7.55 13 9 13h4c1.45 0 3-1.69 3-3.5S14.5 6 13 6z"},"children":[]}]}]},{"type":"text","value":"LMS"}]},{"type":"text","value":"\n"},{"type":"element","tagName":"ul","properties":{},"children":[{"type":"text","value":"\n"},{"type":"element","tagName":"li","properties":{},"children":[{"type":"text","value":"Course code: 2190102"}]},{"type":"text","value":"\n"},{"type":"element","tagName":"li","properties":{},"children":[{"type":"text","value":"Password: "},{"type":"element","tagName":"strong","properties":{},"children":[{"type":"text","value":"advanced"}]}]},{"type":"text","value":"\n"}]},{"type":"text","value":"\n"},{"type":"element","tagName":"h1","properties":{"id":"weekly-learning-format"},"children":[{"type":"element","tagName":"a","properties":{"href":"#weekly-learning-format","ariaHidden":true,"className":["anchor"]},"children":[{"type":"element","tagName":"svg","properties":{"ariaHidden":"true","height":16,"version":"1.1","viewBox":"0 0 16 16","width":16},"children":[{"type":"element","tagName":"path","properties":{"fillRule":"evenodd","d":"M4 9h1v1H4c-1.5 0-3-1.69-3-3.5S2.55 3 4 3h4c1.45 0 3 1.69 3 3.5 0 1.41-.91 2.72-2 3.25V8.59c.58-.45 1-1.27 1-2.09C10 5.22 8.98 4 8 4H4c-.98 0-2 1.22-2 2.5S3 9 4 9zm9-3h-1v1h1c1 0 2 1.22 2 2.5S13.98 12 13 12H9c-.98 0-2-1.22-2-2.5 0-.83.42-1.64 1-2.09V6.25c-1.09.53-2 1.84-2 3.25C6 11.31 7.55 13 9 13h4c1.45 0 3-1.69 3-3.5S14.5 6 13 6z"},"children":[]}]}]},{"type":"text","value":"Weekly Learning Format"}]},{"type":"text","value":"\n"},{"type":"element","tagName":"ul","properties":{},"children":[{"type":"text","value":"\n"},{"type":"element","tagName":"li","properties":{},"children":[{"type":"text","value":"Lecture -> Lab -> Self-Study"}]},{"type":"text","value":"\n"}]},{"type":"text","value":"\n"},{"type":"element","tagName":"h1","properties":{"id":"grading"},"children":[{"type":"element","tagName":"a","properties":{"href":"#grading","ariaHidden":true,"className":["anchor"]},"children":[{"type":"element","tagName":"svg","properties":{"ariaHidden":"true","height":16,"version":"1.1","viewBox":"0 0 16 16","width":16},"children":[{"type":"element","tagName":"path","properties":{"fillRule":"evenodd","d":"M4 9h1v1H4c-1.5 0-3-1.69-3-3.5S2.55 3 4 3h4c1.45 0 3 1.69 3 3.5 0 1.41-.91 2.72-2 3.25V8.59c.58-.45 1-1.27 1-2.09C10 5.22 8.98 4 8 4H4c-.98 0-2 1.22-2 2.5S3 9 4 9zm9-3h-1v1h1c1 0 2 1.22 2 2.5S13.98 12 13 12H9c-.98 0-2-1.22-2-2.5 0-.83.42-1.64 1-2.09V6.25c-1.09.53-2 1.84-2 3.25C6 11.31 7.55 13 9 13h4c1.45 0 3-1.69 3-3.5S14.5 6 13 6z"},"children":[]}]}]},{"type":"text","value":"Grading"}]},{"type":"text","value":"\n"},{"type":"element","tagName":"ul","properties":{},"children":[{"type":"text","value":"\n"},{"type":"element","tagName":"li","properties":{},"children":[{"type":"text","value":"Self-study : 10"}]},{"type":"text","value":"\n"},{"type":"element","tagName":"li","properties":{},"children":[{"type":"text","value":"Final Project : 30"}]},{"type":"text","value":"\n"},{"type":"element","tagName":"li","properties":{},"children":[{"type":"text","value":"Midterm : 30"}]},{"type":"text","value":"\n"},{"type":"element","tagName":"li","properties":{},"children":[{"type":"text","value":"Final : 30"}]},{"type":"text","value":"\n"}]},{"type":"text","value":"\n"},{"type":"element","tagName":"h1","properties":{"id":"course-desc"},"children":[{"type":"element","tagName":"a","properties":{"href":"#course-desc","ariaHidden":true,"className":["anchor"]},"children":[{"type":"element","tagName":"svg","properties":{"ariaHidden":"true","height":16,"version":"1.1","viewBox":"0 0 16 16","width":16},"children":[{"type":"element","tagName":"path","properties":{"fillRule":"evenodd","d":"M4 9h1v1H4c-1.5 0-3-1.69-3-3.5S2.55 3 4 3h4c1.45 0 3 1.69 3 3.5 0 1.41-.91 2.72-2 3.25V8.59c.58-.45 1-1.27 1-2.09C10 5.22 8.98 4 8 4H4c-.98 0-2 1.22-2 2.5S3 9 4 9zm9-3h-1v1h1c1 0 2 1.22 2 2.5S13.98 12 13 12H9c-.98 0-2-1.22-2-2.5 0-.83.42-1.64 1-2.09V6.25c-1.09.53-2 1.84-2 3.25C6 11.31 7.55 13 9 13h4c1.45 0 3-1.69 3-3.5S14.5 6 13 6z"},"children":[]}]}]},{"type":"text","value":"Course Desc"}]},{"type":"text","value":"\n"},{"type":"element","tagName":"ul","properties":{},"children":[{"type":"text","value":"\n"},{"type":"element","tagName":"li","properties":{},"children":[{"type":"text","value":"Full-stack app"}]},{"type":"text","value":"\n"},{"type":"element","tagName":"li","properties":{},"children":[{"type":"text","value":"Services"}]},{"type":"text","value":"\n"},{"type":"element","tagName":"li","properties":{},"children":[{"type":"text","value":"Android"}]},{"type":"text","value":"\n"},{"type":"element","tagName":"li","properties":{},"children":[{"type":"text","value":"Database"}]},{"type":"text","value":"\n"},{"type":"element","tagName":"li","properties":{},"children":[{"type":"text","value":"MongoDB"}]},{"type":"text","value":"\n"},{"type":"element","tagName":"li","properties":{},"children":[{"type":"text","value":"Python"}]},{"type":"text","value":"\n"},{"type":"element","tagName":"li","properties":{},"children":[{"type":"text","value":"Flask"}]},{"type":"text","value":"\n"}]},{"type":"text","value":"\n"},{"type":"element","tagName":"h1","properties":{"id":"chosen-technology"},"children":[{"type":"element","tagName":"a","properties":{"href":"#chosen-technology","ariaHidden":true,"className":["anchor"]},"children":[{"type":"element","tagName":"svg","properties":{"ariaHidden":"true","height":16,"version":"1.1","viewBox":"0 0 16 16","width":16},"children":[{"type":"element","tagName":"path","properties":{"fillRule":"evenodd","d":"M4 9h1v1H4c-1.5 0-3-1.69-3-3.5S2.55 3 4 3h4c1.45 0 3 1.69 3 3.5 0 1.41-.91 2.72-2 3.25V8.59c.58-.45 1-1.27 1-2.09C10 5.22 8.98 4 8 4H4c-.98 0-2 1.22-2 2.5S3 9 4 9zm9-3h-1v1h1c1 0 2 1.22 2 2.5S13.98 12 13 12H9c-.98 0-2-1.22-2-2.5 0-.83.42-1.64 1-2.09V6.25c-1.09.53-2 1.84-2 3.25C6 11.31 7.55 13 9 13h4c1.45 0 3-1.69 3-3.5S14.5 6 13 6z"},"children":[]}]}]},{"type":"text","value":"Chosen Technology"}]},{"type":"text","value":"\n"},{"type":"element","tagName":"ul","properties":{},"children":[{"type":"text","value":"\n"},{"type":"element","tagName":"li","properties":{},"children":[{"type":"text","value":"Python"}]},{"type":"text","value":"\n"},{"type":"element","tagName":"li","properties":{},"children":[{"type":"text","value":"MongoDB"}]},{"type":"text","value":"\n"},{"type":"element","tagName":"li","properties":{},"children":[{"type":"text","value":"Ubuntu"}]},{"type":"text","value":"\n"}]},{"type":"text","value":"\n"},{"type":"element","tagName":"h2","properties":{"id":"python"},"children":[{"type":"element","tagName":"a","properties":{"href":"#python","ariaHidden":true,"className":["anchor"]},"children":[{"type":"element","tagName":"svg","properties":{"ariaHidden":"true","height":16,"version":"1.1","viewBox":"0 0 16 16","width":16},"children":[{"type":"element","tagName":"path","properties":{"fillRule":"evenodd","d":"M4 9h1v1H4c-1.5 0-3-1.69-3-3.5S2.55 3 4 3h4c1.45 0 3 1.69 3 3.5 0 1.41-.91 2.72-2 3.25V8.59c.58-.45 1-1.27 1-2.09C10 5.22 8.98 4 8 4H4c-.98 0-2 1.22-2 2.5S3 9 4 9zm9-3h-1v1h1c1 0 2 1.22 2 2.5S13.98 12 13 12H9c-.98 0-2-1.22-2-2.5 0-.83.42-1.64 1-2.09V6.25c-1.09.53-2 1.84-2 3.25C6 11.31 7.55 13 9 13h4c1.45 0 3-1.69 3-3.5S14.5 6 13 6z"},"children":[]}]}]},{"type":"text","value":"Python"}]},{"type":"text","value":"\n"},{"type":"element","tagName":"ul","properties":{},"children":[{"type":"text","value":"\n"},{"type":"element","tagName":"li","properties":{},"children":[{"type":"text","value":"Interactive program/ interpreter"}]},{"type":"text","value":"\n"},{"type":"element","tagName":"li","properties":{},"children":[{"type":"text","value":"Fast prototyping language"}]},{"type":"text","value":"\n"},{"type":"element","tagName":"li","properties":{},"children":[{"type":"text","value":"Useful for many area"}]},{"type":"text","value":"\n"},{"type":"element","tagName":"li","properties":{},"children":[{"type":"text","value":"Server side application"}]},{"type":"text","value":"\n"}]},{"type":"text","value":"\n"},{"type":"element","tagName":"h2","properties":{"id":"ubuntu"},"children":[{"type":"element","tagName":"a","properties":{"href":"#ubuntu","ariaHidden":true,"className":["anchor"]},"children":[{"type":"element","tagName":"svg","properties":{"ariaHidden":"true","height":16,"version":"1.1","viewBox":"0 0 16 16","width":16},"children":[{"type":"element","tagName":"path","properties":{"fillRule":"evenodd","d":"M4 9h1v1H4c-1.5 0-3-1.69-3-3.5S2.55 3 4 3h4c1.45 0 3 1.69 3 3.5 0 1.41-.91 2.72-2 3.25V8.59c.58-.45 1-1.27 1-2.09C10 5.22 8.98 4 8 4H4c-.98 0-2 1.22-2 2.5S3 9 4 9zm9-3h-1v1h1c1 0 2 1.22 2 2.5S13.98 12 13 12H9c-.98 0-2-1.22-2-2.5 0-.83.42-1.64 1-2.09V6.25c-1.09.53-2 1.84-2 3.25C6 11.31 7.55 13 9 13h4c1.45 0 3-1.69 3-3.5S14.5 6 13 6z"},"children":[]}]}]},{"type":"text","value":"Ubuntu"}]},{"type":"text","value":"\n"},{"type":"element","tagName":"ul","properties":{},"children":[{"type":"text","value":"\n"},{"type":"element","tagName":"li","properties":{},"children":[{"type":"text","value":"Widely used Linux distrbution"}]},{"type":"text","value":"\n"},{"type":"element","tagName":"li","properties":{},"children":[{"type":"text","value":"Avaiable on many cloud services"}]},{"type":"text","value":"\n"},{"type":"element","tagName":"li","properties":{},"children":[{"type":"text","value":"We’ll be using Ubuntu Server"}]},{"type":"text","value":"\n"}]},{"type":"text","value":"\n"},{"type":"element","tagName":"h2","properties":{"id":"mongodb"},"children":[{"type":"element","tagName":"a","properties":{"href":"#mongodb","ariaHidden":true,"className":["anchor"]},"children":[{"type":"element","tagName":"svg","properties":{"ariaHidden":"true","height":16,"version":"1.1","viewBox":"0 0 16 16","width":16},"children":[{"type":"element","tagName":"path","properties":{"fillRule":"evenodd","d":"M4 9h1v1H4c-1.5 0-3-1.69-3-3.5S2.55 3 4 3h4c1.45 0 3 1.69 3 3.5 0 1.41-.91 2.72-2 3.25V8.59c.58-.45 1-1.27 1-2.09C10 5.22 8.98 4 8 4H4c-.98 0-2 1.22-2 2.5S3 9 4 9zm9-3h-1v1h1c1 0 2 1.22 2 2.5S13.98 12 13 12H9c-.98 0-2-1.22-2-2.5 0-.83.42-1.64 1-2.09V6.25c-1.09.53-2 1.84-2 3.25C6 11.31 7.55 13 9 13h4c1.45 0 3-1.69 3-3.5S14.5 6 13 6z"},"children":[]}]}]},{"type":"text","value":"MongoDB"}]},{"type":"text","value":"\n"},{"type":"element","tagName":"ul","properties":{},"children":[{"type":"text","value":"\n"},{"type":"element","tagName":"li","properties":{},"children":[{"type":"text","value":"Free document-oriented database"}]},{"type":"text","value":"\n"},{"type":"element","tagName":"li","properties":{},"children":[{"type":"text","value":"NoSQL"}]},{"type":"text","value":"\n"},{"type":"element","tagName":"li","properties":{},"children":[{"type":"text","value":"JSON-like document with schemata"}]},{"type":"text","value":"\n"}]},{"type":"text","value":"\n"},{"type":"element","tagName":"h1","properties":{"id":"service"},"children":[{"type":"element","tagName":"a","properties":{"href":"#service","ariaHidden":true,"className":["anchor"]},"children":[{"type":"element","tagName":"svg","properties":{"ariaHidden":"true","height":16,"version":"1.1","viewBox":"0 0 16 16","width":16},"children":[{"type":"element","tagName":"path","properties":{"fillRule":"evenodd","d":"M4 9h1v1H4c-1.5 0-3-1.69-3-3.5S2.55 3 4 3h4c1.45 0 3 1.69 3 3.5 0 1.41-.91 2.72-2 3.25V8.59c.58-.45 1-1.27 1-2.09C10 5.22 8.98 4 8 4H4c-.98 0-2 1.22-2 2.5S3 9 4 9zm9-3h-1v1h1c1 0 2 1.22 2 2.5S13.98 12 13 12H9c-.98 0-2-1.22-2-2.5 0-.83.42-1.64 1-2.09V6.25c-1.09.53-2 1.84-2 3.25C6 11.31 7.55 13 9 13h4c1.45 0 3-1.69 3-3.5S14.5 6 13 6z"},"children":[]}]}]},{"type":"text","value":"Service"}]},{"type":"text","value":"\n"},{"type":"element","tagName":"ul","properties":{},"children":[{"type":"text","value":"\n"},{"type":"element","tagName":"li","properties":{},"children":[{"type":"text","value":"Android application will call service on your Python or using a native library such as Facebook API or other database"}]},{"type":"text","value":"\n"}]},{"type":"text","value":"\n"},{"type":"element","tagName":"h1","properties":{"id":"android-studio"},"children":[{"type":"element","tagName":"a","properties":{"href":"#android-studio","ariaHidden":true,"className":["anchor"]},"children":[{"type":"element","tagName":"svg","properties":{"ariaHidden":"true","height":16,"version":"1.1","viewBox":"0 0 16 16","width":16},"children":[{"type":"element","tagName":"path","properties":{"fillRule":"evenodd","d":"M4 9h1v1H4c-1.5 0-3-1.69-3-3.5S2.55 3 4 3h4c1.45 0 3 1.69 3 3.5 0 1.41-.91 2.72-2 3.25V8.59c.58-.45 1-1.27 1-2.09C10 5.22 8.98 4 8 4H4c-.98 0-2 1.22-2 2.5S3 9 4 9zm9-3h-1v1h1c1 0 2 1.22 2 2.5S13.98 12 13 12H9c-.98 0-2-1.22-2-2.5 0-.83.42-1.64 1-2.09V6.25c-1.09.53-2 1.84-2 3.25C6 11.31 7.55 13 9 13h4c1.45 0 3-1.69 3-3.5S14.5 6 13 6z"},"children":[]}]}]},{"type":"text","value":"Android Studio"}]},{"type":"text","value":"\n"},{"type":"element","tagName":"ul","properties":{},"children":[{"type":"text","value":"\n"},{"type":"element","tagName":"li","properties":{},"children":[{"type":"text","value":"Official IDE for Android"}]},{"type":"text","value":"\n"},{"type":"element","tagName":"li","properties":{},"children":[{"type":"text","value":"Java Language"}]},{"type":"text","value":"\n"},{"type":"element","tagName":"li","properties":{},"children":[{"type":"text","value":"Integrated UI"}]},{"type":"text","value":"\n"},{"type":"element","tagName":"li","properties":{},"children":[{"type":"text","value":"Addition APIs for Android Application"}]},{"type":"text","value":"\n"}]},{"type":"text","value":"\n"},{"type":"element","tagName":"h1","properties":{"id":"lab"},"children":[{"type":"element","tagName":"a","properties":{"href":"#lab","ariaHidden":true,"className":["anchor"]},"children":[{"type":"element","tagName":"svg","properties":{"ariaHidden":"true","height":16,"version":"1.1","viewBox":"0 0 16 16","width":16},"children":[{"type":"element","tagName":"path","properties":{"fillRule":"evenodd","d":"M4 9h1v1H4c-1.5 0-3-1.69-3-3.5S2.55 3 4 3h4c1.45 0 3 1.69 3 3.5 0 1.41-.91 2.72-2 3.25V8.59c.58-.45 1-1.27 1-2.09C10 5.22 8.98 4 8 4H4c-.98 0-2 1.22-2 2.5S3 9 4 9zm9-3h-1v1h1c1 0 2 1.22 2 2.5S13.98 12 13 12H9c-.98 0-2-1.22-2-2.5 0-.83.42-1.64 1-2.09V6.25c-1.09.53-2 1.84-2 3.25C6 11.31 7.55 13 9 13h4c1.45 0 3-1.69 3-3.5S14.5 6 13 6z"},"children":[]}]}]},{"type":"text","value":"Lab"}]},{"type":"text","value":"\n"},{"type":"element","tagName":"ul","properties":{},"children":[{"type":"text","value":"\n"},{"type":"element","tagName":"li","properties":{},"children":[{"type":"text","value":"Individual or Small group"}]},{"type":"text","value":"\n"},{"type":"element","tagName":"li","properties":{},"children":[{"type":"text","value":"Finish / Submit on CourseVille"}]},{"type":"text","value":"\n"},{"type":"element","tagName":"li","properties":{},"children":[{"type":"text","value":"Bring laptic if you can"}]},{"type":"text","value":"\n"}]},{"type":"text","value":"\n"},{"type":"element","tagName":"h1","properties":{"id":"final-project"},"children":[{"type":"element","tagName":"a","properties":{"href":"#final-project","ariaHidden":true,"className":["anchor"]},"children":[{"type":"element","tagName":"svg","properties":{"ariaHidden":"true","height":16,"version":"1.1","viewBox":"0 0 16 16","width":16},"children":[{"type":"element","tagName":"path","properties":{"fillRule":"evenodd","d":"M4 9h1v1H4c-1.5 0-3-1.69-3-3.5S2.55 3 4 3h4c1.45 0 3 1.69 3 3.5 0 1.41-.91 2.72-2 3.25V8.59c.58-.45 1-1.27 1-2.09C10 5.22 8.98 4 8 4H4c-.98 0-2 1.22-2 2.5S3 9 4 9zm9-3h-1v1h1c1 0 2 1.22 2 2.5S13.98 12 13 12H9c-.98 0-2-1.22-2-2.5 0-.83.42-1.64 1-2.09V6.25c-1.09.53-2 1.84-2 3.25C6 11.31 7.55 13 9 13h4c1.45 0 3-1.69 3-3.5S14.5 6 13 6z"},"children":[]}]}]},{"type":"text","value":"Final project"}]},{"type":"text","value":"\n"},{"type":"element","tagName":"ul","properties":{},"children":[{"type":"text","value":"\n"},{"type":"element","tagName":"li","properties":{},"children":[{"type":"text","value":"\n"},{"type":"element","tagName":"p","properties":{},"children":[{"type":"text","value":"Tentative"}]},{"type":"text","value":"\n"},{"type":"element","tagName":"ul","properties":{},"children":[{"type":"text","value":"\n"},{"type":"element","tagName":"li","properties":{},"children":[{"type":"text","value":"Fully working mobile application"}]},{"type":"text","value":"\n"},{"type":"element","tagName":"li","properties":{},"children":[{"type":"text","value":"Android Application"}]},{"type":"text","value":"\n"},{"type":"element","tagName":"li","properties":{},"children":[{"type":"text","value":"Python as a service"}]},{"type":"text","value":"\n"},{"type":"element","tagName":"li","properties":{},"children":[{"type":"text","value":"Some kind of database and record"}]},{"type":"text","value":"\n"}]},{"type":"text","value":"\n"}]},{"type":"text","value":"\n"},{"type":"element","tagName":"li","properties":{},"children":[{"type":"text","value":"Starting after midterm"}]},{"type":"text","value":"\n"},{"type":"element","tagName":"li","properties":{},"children":[{"type":"text","value":"Final requirement later"}]},{"type":"text","value":"\n"}]}],"data":{"quirksMode":false}},"frontmatter":{"title":"Introduction","subject":"Advanced Computer Programming","date":"August 16, 2018"}}},"pageContext":{"slug":"/advanced-computer-programming/01-Introduction/","previous":{"fields":{"slug":"/history-of-science/01-orientation/"},"frontmatter":{"title":"Introduction","subject":"History of Science"}},"next":{"fields":{"slug":"/electrical-circuit-for-ice/01-introduction/"},"frontmatter":{"title":"Introduction","subject":"Electrical Circuit for ICE"}}}}